odoo8_addon_web_x2m_defaults_from_previous-8.0.1.0.0-py2.7-nspkg.pth
odoo8_addon_web_x2m_defaults_from_previous-8.0.1.0.0.dist-info/top_level.txt
odoo8_addon_web_x2m_defaults_from_previous-8.0.1.0.0.dist-info/WHEEL
odoo8_addon_web_x2m_defaults_from_previous-8.0.1.0.0.dist-info/RECORD
odoo8_addon_web_x2m_defaults_from_previous-8.0.1.0.0.dist-info/metadata.json
odoo8_addon_web_x2m_defaults_from_previous-8.0.1.0.0.dist-info/DESCRIPTION.rst
odoo8_addon_web_x2m_defaults_from_previous-8.0.1.0.0.dist-info/METADATA
odoo8_addon_web_x2m_defaults_from_previous-8.0.1.0.0.dist-info/namespace_packages.txt
odoo_addons/web_x2m_defaults_from_previous/__openerp__.py
odoo_addons/web_x2m_defaults_from_previous/__init__.py
odoo_addons/web_x2m_defaults_from_previous/README.rst
odoo_addons/web_x2m_defaults_from_previous/views/templates.xml
odoo_addons/web_x2m_defaults_from_previous/demo/ir_ui_view.xml
odoo_addons/web_x2m_defaults_from_previous/static/description/icon.png
odoo_addons/web_x2m_defaults_from_previous/static/src/js/web_x2m_defaults_from_previous.js
